misc/__init__.py
misc/beam_search.py
misc/dataset.py
misc/early_stopping.py
misc/graph.py
misc/loggers.py
misc/optimizer.py
misc/preprocess.py
misc/trainer.py
modules/__init__.py
modules/attention.py
modules/custom.py
modules/decoder.py
modules/encoder.py
modules/encoder_decoder.py
modules/lm.py
modules/utils.py
seqmod/__init__.py
seqmod/misc/__init__.py
seqmod/misc/beam_search.py
seqmod/misc/dataset.py
seqmod/misc/early_stopping.py
seqmod/misc/graph.py
seqmod/misc/loggers.py
seqmod/misc/optimizer.py
seqmod/misc/preprocess.py
seqmod/misc/trainer.py
seqmod/modules/__init__.py
seqmod/modules/attention.py
seqmod/modules/custom.py
seqmod/modules/decoder.py
seqmod/modules/encoder.py
seqmod/modules/encoder_decoder.py
seqmod/modules/lm.py
seqmod/modules/utils.py
seqmod-0.1.dist-info/DESCRIPTION.rst
seqmod-0.1.dist-info/METADATA
seqmod-0.1.dist-info/RECORD
seqmod-0.1.dist-info/WHEEL
seqmod-0.1.dist-info/metadata.json
seqmod-0.1.dist-info/top_level.txt
