Metadata-Version: 2.0
Name: seqmod
Version: 0.1
Summary: Pytorch implementations of sequence modellers for language
Home-page: https://www.github.com/emanjavacas/seqmod/
Author: Enrique Manjavacas
Author-email: enrique.manjavacas@gmail.com
License: MIT
Download-URL: https://api.github.com/repos/emanjavacas/seqmod/tarball
Platform: UNKNOWN
Requires-Dist: graphviz (>=0.5.2)
Requires-Dist: numpy (>=1.10.4)
Requires-Dist: torch (>=0.1.10+ac9245a)
Requires-Dist: visdom (>=0.1.2)
